pydantic_flagged/__init__.py
pydantic_flagged/dump.py
pydantic_flagged/main.py
pydantic_flagged-0.0.1.dist-info/METADATA
pydantic_flagged-0.0.1.dist-info/WHEEL
pydantic_flagged-0.0.1.dist-info/licenses/LICENSE
pydantic_flagged-0.0.1.dist-info/RECORD
