Metadata-Version: 2.4
Name: pydantic-flagged
Version: 0.0.1
Summary: Pydantic BaseModel with flagged fields by name
Author-email: Ryan Young <dev@ryayoung.com>
License-Expression: MIT
License-File: LICENSE
Classifier: Development Status :: 3 - Alpha
Classifier: Intended Audience :: Developers
Classifier: License :: OSI Approved :: MIT License
Classifier: Operating System :: OS Independent
Classifier: Programming Language :: Python :: 3.12
Classifier: Topic :: Software Development :: Libraries
Requires-Dist: pydantic<3.0,>=2.0
